commonhealth_cloud_storage_client/__init__.py
commonhealth_cloud_storage_client/client.py
commonhealth_cloud_storage_client/crypto.py
commonhealth_cloud_storage_client/errors.py
commonhealth_cloud_storage_client/jwt.py
commonhealth_cloud_storage_client/sqlite_delegate.py
commonhealth_cloud_storage_client-1.0.5.dist-info/LICENSE
commonhealth_cloud_storage_client-1.0.5.dist-info/METADATA
commonhealth_cloud_storage_client-1.0.5.dist-info/WHEEL
commonhealth_cloud_storage_client-1.0.5.dist-info/top_level.txt
commonhealth_cloud_storage_client-1.0.5.dist-info/RECORD
